nested_attrs/__init__.py
nested_attrs-0.1.0.dist-info/LICENSE
nested_attrs-0.1.0.dist-info/METADATA
nested_attrs-0.1.0.dist-info/WHEEL
nested_attrs-0.1.0.dist-info/top_level.txt
nested_attrs-0.1.0.dist-info/RECORD
