Metadata-Version: 2.1
Name: nested-attrs
Version: 0.1.0
Summary: Just some small helpers for nested attributes
Home-page: https://github.com/spenserblack/nested-attrs
License: MIT
Project-URL: Bug Tracker, https://github.com/spenserblack/nested-attrs/issues
Keywords: attr,attrs,nested
Classifier: Programming Language :: Python :: 3
Requires-Python: >=3.6
License-File: LICENSE
